darkgrey/__init__.py
darkgrey-0.0.dist-info/WHEEL
darkgrey-0.0.dist-info/METADATA
darkgrey-0.0.dist-info/RECORD
