Metadata-Version: 2.1
Name: darkgrey
Version: 0.0
Summary: Close to black.
Home-page: UNKNOWN
License: UNKNOWN
Author: Éric Araujo
Author-email: merwok@netwok.org
